[{
        "Title": "Chodo-Algo For learners",
        "Content": "Chodo Algo, is a Moroccan Algorithm Plugin For Notpad++ Made By Chodo Brothers Community (francophone) OFPPT  <br><a href=\"https://github.com/Baronsindo/Chodo-Algo\" target=\"_blank\">Consult repositorie</a>",
        "Tag": "Codes",
        "Image": "./Images/Algo.png"

    },
    {
        "Title": "ุงูุฃูุชุฑูุช ุงูุนููู ู ุงููุถูู",
        "Content": "ุงูุฃูุชุฑูุช ูู ููุดูููู ูุงุดู ุบูุฑ ูู ูู ููู ููู ุญุชุง ุงูุฃูุชุฑูุช ุงูุนููู ู ุงูุฃูุชุฑูุช ุงููุถูู ูู ุนุงูุฑ ุจุงูุฃุณุฑุงุฑ ููููุง ุดููุง ูุงููุณุณูุณู ุฏูุงู ูุณุชุฑ ุฑูุจูุช, ููุจูุนู ุงููุฎุฏุฑุงุช ู ุงูุฃุณูุญุฉ ู ุฌููุน ุงูุฃุดูุงุก ุงููุญุฑูุฉ ูุงูุฃูุชุฑูุช ูู ูููุฏู ููุตูู ููู, ูุงุฏ ุงูุฃูุชุฑูุช ุฎุงุตู ุบูุฑ ููููู ุนูุฏู ููููุณ ู ุบุงุฏู ุชูุฏ ุฏูุฑ ุฃู ุญุงุฌุฉ ูู ุงูููุฏูููุงุช ุงูุฅุจุงุญูุฉ ุงูุดุงุฏุฉ ุญุชุงู ุชูุถูู ุฌูุด ุฃู ูุฑุชุฒูุฉ ุชุฎุฏู ูุตุงูุญู. ููุณูู ูุฐุง ุงูุฅูุชุฑูุช ุงููุธููุ ุฃุฑุถ ุงูุฎุฏูุงุช ุงููุฎููุฉุ ุญูุซ ูุชููุฒ ุจุนุฏู ุชุฑู ุงู ุขุซุงุฑ ู ุนุฏู ุงููุดู ุนู ูููุฉ ุงููุณุชุฎุฏู. ุฎูุฏู ุงูุญูุทุฉ ู ุงูุญุฐุฑ ูุฃุบูุจ ุงููุงุณ ูู ููู ูุฎุชุฑููู ูุชูุฑุณูู ุฃู ูุฌุฑููู ุฎุทูุฑูู ุนุงุฏ ุฒูุฏ ุฃุนูู ุงูุดุฑุทุฉ ูู ูุชููุจ ุนูู ุดู ุฑุงุณ ุฏูุงู ุงูุฎูุท ุจุงุด ุชูุตู ูููู. ูุงุชูุณุงูุด ุชุดุชุงุฑูู ุงู ุฎููู ููุง ุงูููุถูุน ูู ููุฏุฑ ุนููู ุงููุฑุฉ ุงูุฌุงูุฉ.",
        "Image": "./Images/Deep.jpg",
        "Tag": "Blog"
    },
    {
        "Title": "ููุงู ูุฑุฏู ูุงุญุฏ ุงูุดููุฉ",
        "Content": "ูุงุญุฏ ุงูููุงู ูุฑุฏู ูุงุญุฏ ุงูุดููุฉ ูุงุฏุง ูุงุญุฏ ุงููุฑุฏ ๐ ุฎูุงู ุฃู ููุฎุงู ุจุฒุงุงู ููุฏุงูุดู ูู ููููููู ุงููุฑูุฏุฉ ๐ ุงูุขุฎุฑูู ุนููู ุฏุงูุดู ูุงุด ููุจุบู ูููู ุจุญุงู ๐ ุงููุฑูุฏุฉ ุงูุฎุฑูู ุจุงุด ููููู ูุจุบููู ู ููู ูุงุฏ ุงููุถูุฉ ุตุนูุจุฉ ุญูุงุด ๐ ุงููุฑูุฏุฉ ูู ุงูุญููุงูุงุช ูู ููุนุฑูู ููุฑููุ ๐ ุงููุฑุฏ ูููุญููุด ๐ ุงููุฑุฏ ูู ูุฎุชุงูู ุนููู ู ูุง ๐ุงููุฑุฏ ูู ูู ุจูุงุตุฉ ูุญุฏุฉ ุขุฎุฑู ู ูุง ๐ุงููุฑุฏ ูู ุนูุฏู ููู ูุฎุชุงููุ ุฃู ูุงูุขุฎุฑ ููุจุฏุง ูุงุฏ ๐ ุงููุฑุฏ ูุญุณ ุจุงููุญุฏุฉ ูุงุฎุง ููููู ุจุฒุงุงุงู ุฏูุงู ๐ุงููุฑูุฏุฉ ุญุฏุงู. ุฃู ุญูุง ูุจุดุฑ ๐ง๐ง ุนูุฏูุง ูุนููุฑุฉ ุชููู ูุดู ุญุฏ ุญููุงู ู ุจูุง ุฃู ๐ุงููุฑูุฏุฉ ุญููุงูุงุช ู ุญูุง ููุฏูุฑู ุจุญุงููู ุฑุงู ุชุญูู ุญููุงูุงุช ุจุญุงู ุฃู ๐ ูุฑุฏุ ู ุจุงุงุงุงุฑุงูุง ูู ุงููุนุงูู ุฏูุงู ๐ ุงููุฑูุฏุฉ ู ุฎููููุง ููููู ุจุดุฑ ูู ููุจูู ุฎุงูู ูู ุงูุญูุฏ ู ุนุงูุฑ ุจุงูุงูุณุงููุฉ.",
        "Image": "./Images/Ape.jpg",
        "Tag": "Blog"
    },
    {
        "Title": "ููุณุงุฌ ุจุงุด ูุชูุดูุด",
        "Content": "ุจุงุบู ูุฒูุฏ ููุฏุงู ูููุฏูุชุด ุตุงูู ุนููุช ูุบุงุฏู ูุญุจุณ ููุง ุดุญุงุงุงู ูู ูุงุญุฏ ูุทุฑุง ููู ุฏูู ุงููุทุฉ ูุงุด ููุญุณ ุงูู ูุดู ูุตุงูู ูุจูุงุด ูุงุฏ ููููุ ู ุงูุง ุฌููุง ูุดููู ุบุฏู ูููุงูู ุนูุฏู ุจุฒุงุงุงุงู ุฏูุงู ูุญููุฌ ูู ูุชูููู ุนููู ู ููุฎููููุด ููุตู ูุฏุงูุดู ูู ุจุงุบู ุชูุฏุฑ ุชููู ุจููุฉ ููุง ุนูุงูุฉ ุบูุฑ ุนุงุจุฑุฉ ุบุงุฏู ุชุฑุจุญู ูุงูุงุฎุฑ ุฏุฑุณ ููุฏุฑ ูููุนู ููุฏุฑ ูุงุ ููุง ุบูุฑ ุญููุฌ ุตุบุงุงุฑ ุจุญุงู ุดู ูุณูุณู ููุง ุฃููู ูู ุชูุฏุฑ ุชูุฑุฌ ูุณุชุฉ ุฏูุงู ุงูุญููุงุช ูุฑุงุฏููู ู ูุชุญุณุด ุจุงูููุช ูู ุถุงุน ููู ูุงูุฃุฎูุฑ. ุฅูู ุจุบูุชู ุชุฒูุฏ ููุฏุงู ู ููุฏูุชูุด ููุญ ุฏุงู ุงูุชูู ู ุงูุจุนุฑ ูู ูุชูู ุนูู ุถูุฑู ูุฑุฎู ููู ุงูููุณ ูุบุชุฒูุฏ ููุฏุงู ูุฏูููุง ุชููุฑ ุจูุง \" ุฅูุง ูุถุญูุชูุด ุนูู ูุญููุฌ ูู ุจุงุบู ููุง ูุชุจุบู ุฅุฏู ุฑุงู ูุถุญู ุจููู\". ูุงุฏ ุงูููุณุงุฌ ูุงุชุจู ูุฑุงุณู ูุจู ูู ุฃู ูุงุญุฏ ุบูุดููู ุญูุงุด ูุงูููู ููุชูุงูุงู ู ููุณุงู ุงูุงููููุงุช ุฏูุงููุง. ุนูู ุงููู ุดู ูุฑุฉ ูููุฏุฑุด ูููู ุชุง ุฃูุง ููุดูููุ ููุนุทููู ููู ุฏูุนุฉ ุตุบููุฑุฉ ุจุงุด ูุฒูุฏ ููุฏุงู.",
        "Image": "./Images/Down.jpg",
        "Tag": "Blog"
    },
    {
        "Title": "ุนูุฏูู ููู ุงูุญู",
        "Content": "ุฏุงุจุง ููู ูููุงุฏู ุดู ุฃุจูููุงุณููู ู ููููุญููุง ูุงูุตุทูุฑ ู ูุง ููุนุทูู ูุดู ุดุฑูุฉ ููุง ุดู ูุณุชุฎุฏู ู ุฏูู ุงูุฃุจูููุงุณููู ูุชุจุฏู ุฏูุฑ ุงููุดุงููุ ุฃูู ูุงุญุฏ ููููุฑ ููู ุงููุณุชุฎุฏู ูู ุงูุดุฎุต ูู ุตูุน ุฏูู ุงูุขุจ ุญูุงุด ูู ูู ุบูููู ุนูุฏู ุงูุญู.<br> ููู ูููููู ุนูุดูู ููุงุฏ ุงูุฏููุง ู ููุจุฏุงู ููุชุฑู ุนูููุง ุงููุดุงูู ุฏูุงููุง ู ููุจุฏุงู ูุจุฑุฒุทููุง ูุญูุงุชูุง ูู ุฃุตูุง ูุตูุฑุฉ ู ุงูุซูุช ุฏูุงููุง ูุนุงุณุ ุฎุงุตูุง ููุดูู ููุฌุฑูู ุนูุฏ ูู ุตูุนูุง ุญูุงุด ูู ูู ุนูุฏู ุงูุญู ุฎุงุตูุง ููุดูู ุนูุฏ ุงููู ูู ุนูุฏู ููู ูุฑุจ ูุฑุฌ ู ููู ุนุณุฑ ูุณุฑ ุญูุง ูุงุฎุง ุถุนุงู ุบูููุงู ุฅูู ุงุณุชุนูุง ุจุงููู.",
        "Image": "./Images/Solution.jpg",
        "Tag": "Blog"
    },
    {
        "Title": "ุงููุฑูุณูุฉ ูุบุฉ ููุจุนููู",
        "Content": "ุงููุบุฉ ุงููุฑูุณูุฉ ููุงุฏ ุงูุจูุงุฏ ุทุงุบูุฉ ุจุฒุงุงู ู ุฏุงุฎูุง ููุงุน ุงููุฌุงูุงุช ูููุง ูุนูุฏูุด ูุงุฎุง ุชููู ุทููุจ ูุงูุถูููู ูุบุชููุงุด ุจูุงุตุชู ููุตุญูู ุชุนููู ูุบุฉ ุงูููุงุฑ ููุจุนููู ูุจุบูุชู ุชุฎุฏูู. ู ุงููู ููุฌููู ูู ุงููุฑูููููููู ูุง ูุงูููู ุจุฑูู ุญูุงุด ููุฑุง ูุงุฏ ุงููููุฉ ููุชุจูู ุชูุดุจู ูุงูู ููุฌูุจ ููู ุดู ูููุฉ ูุชุนูู ุชูุงุชุฉ ููุง ุฑุจุนุฉ ุฏูุงู ุงููููุงุช ุฏูุฉ ูุญุฏุฉ ูู ุฏูู ุงูุตูุญุฉ ููุบุจุฑุฉ ูุงูุฏููุณููููุฑ ููููููููููู.",
        "Image": "./Images/France.jpg",
        "Tag": "Blog"
    },
    {
        "Title": "ุงููุจุฑูุงุก ู ุงูุญููุฉ",
        "Content": "ููู ุงููุจุฑูุงุก ููููู ููู : \" ุฏูุฑูุง ุบูุฑ ุฑุงุณู \"ุ ูููู ุงูุญููุฉ ูุชููู ููู : \" ุทูุจ ุงูุนูู ูู ุดู ุญุฏ \"ุ ููู ูุชูุงุถุน ุดููุฉ ู ุชุตูุช ููุญููุฉุ ุบุชููู ูุฎูุฑ ุญูุช ุฏุฑุชููุง ูุงุญุฏ ุงูููุงุฑ. ูุฃุบูุจ ุงูุฃููุงุช ุฃูุง ููุชุตูุช ุบูุฑ ูููุจุฑูุงุก ู ููู ููุฌู ุงูููุช ุฏูุงู ุงููุฏู ูู ููุช ูู ููููู ูุนุงูุง ู ููุฌุจุฏ ููุง 100 ุณุจุฉุ ููููู : \"ููู ุตุฏูุงุช ู ุฏุฑุชููุง ุบูุฑ ุฑุงุณู ููุชู ุบุชูุฑุญ ูุชุฑ\" ู ููุชููู ุฃูุง ููุดู ุญูุงุฑ. ุงููุฑุฉ ุงูุฌุงูุง ุนุงุฑู ุฑุงุณู ุบุงุฏู ูุชุตูุช ููู ุญูุงุด ููู ูููุฏููุงุด ูููุ ูููุจุณ ุซูุจ ุงูุญููุฉ ู ููุฌู ุนูุฏู.",
        "Image": "./Images/Pride.png",
        "Tag": "Blog"
    },
    {
        "Title": "Test",
        "Content": "Just For test",
        "Image": "./Images/User.jpg",
        "Tag": "Blog"
    },
    {
        "Title": "BTS K-pop Lyrics",
        "Content": "Here You can find all Lyrics of BTS, EXO, Big Bang,Red Velvet and Twice's songs, Let me guss You Like BTS, EXO, Big Bang,Red Velvet and Twice and K-pop ? and You want one app that Contain all Lyrics and made by K-popers For K-popers Dont u ?<br>then let me tell You this app Has every Singel song Lyrics Of BTS, EXO, Big Bang,Red Velvet and Twice So now you can sing Korean songs of BTS, EXO, Big Bang,Red Velvet and Twice <br>And if you wanna Make Songs cover it will Help You a lot TO do this Jop .<br>we Keep updating our apps with every song and come back You can check in our other K-pop apps , and we have full song lyrics<br><br>In this application :<br><br>- you can find all lyrics of BTS, EXO, Big Bang,Red Velvet and Twice K-pop band . <br>- You can favorite Lyrics easily And display them on favorites list.<br>- you can also Share your favorite lyrics of BTS, EXO, Big Bang,Red Velvet and Twice band with your friends, in all social networks Like Facebook or Whatsapp or Email .<br>- Good design and easy to access and understand <br>- healthy colors for You eyes .<br>- you can find BTS, EXO, Big Bang,Red Velvet and Twice Lyrics in English and Romanized and also .<br>- You can search By album Or by Song <br><br>- This application only for entertainments purposes.<br>- This application does not make any violate the trademark of any music companies.<br>- Please support the artists and their companies. Buy the original CDs, MP3s, videos and merchandise.<br><br>Please contact us if any kind of suggestions or comments about this application.<br>dear User of Chรดdos application of BTS, EXO, Big Bang,Red Velvet and Twice Lyrics if you want to see you language in our BTS, EXO, Big Bang,Red Velvet and Twice app please send your lyrics to Chรดdo and Chรดdo will puts your lyrics in the BTS, EXO, Big Bang,Red Velvet and Twice Lyrics app and as a thanks we'il put your name in the about section of BTS, EXO, Big Bang,Red Velvet and Twice lyrics app Like this \" this lyrics was generated by BTS, EXO, Big Bang,Red Velvet and Twice app YourName \" <br>please like our company \"Chรดdo - apps\" in facebook and twitter , and look in our other apps you might like them ;<br><br>Try This app and you'il never regret<br><br><a href=\"https://play.google.com/store/apps/details?id=com.Chodo.BTSLyrics\" target=\"_blank\">BTS K-pop Lyrics</a>",
        "Image": "./Images/BTS.png",
        "Tag": "Codes"
    }
]
